{"swagger":"2.0","info":{"title":"Fieldkit API","description":"A one-click open platform for field researchers and explorers.","version":""},"host":"api.data.fieldkit.org","schemes":["https"],"consumes":["application/json"],"produces":["application/json"],"paths":{"/expeditions/{expedition_id}":{"get":{"tags":["expedition"],"summary":"get id expedition","description":"Add a expedition\n\nRequired security scopes:\n  * `api:access`","operationId":"expedition#get id","produces":["application/vnd.app.expedition+json"],"parameters":[{"name":"expedition_id","in":"path","required":true,"type":"integer"}],"responses":{"200":{"description":"OK","schema":{"$ref":"#/definitions/Expedition"}},"400":{"description":"Bad Request"}},"schemes":["https"],"security":[{"jwt":["api:access"]}]}},"/expeditions/{expedition_id}/inputs":{"get":{"tags":["input"],"summary":"list id input","description":"List a project's inputs\n\nRequired security scopes:\n  * `api:access`","operationId":"input#list id","produces":["application/vnd.app.inputs+json"],"parameters":[{"name":"expedition_id","in":"path","required":true,"type":"integer"}],"responses":{"200":{"description":"OK","schema":{"$ref":"#/definitions/Inputs"}},"400":{"description":"Bad Request"}},"schemes":["https"],"security":[{"jwt":["api:access"]}]}},"/expeditions/{expedition_id}/inputs/twitter-account":{"post":{"tags":["twitter"],"summary":"add twitter","description":"Add a Twitter account input\n\nRequired security scopes:\n  * `api:access`","operationId":"twitter#add","produces":["application/vnd.app.location+json"],"parameters":[{"name":"expedition_id","in":"path","required":true,"type":"integer"}],"responses":{"200":{"description":"OK","schema":{"$ref":"#/definitions/Location"}},"400":{"description":"Bad Request"}},"schemes":["https"],"security":[{"jwt":["api:access"]}]}},"/expeditions/{expedition_id}/inputs/twitter-accounts":{"get":{"tags":["twitter"],"summary":"list id twitter","description":"List an expedition's Twitter account inputs\n\nRequired security scopes:\n  * `api:access`","operationId":"twitter#list id","produces":["application/vnd.app.twitter_accounts+json"],"parameters":[{"name":"expedition_id","in":"path","required":true,"type":"integer"}],"responses":{"200":{"description":"OK","schema":{"$ref":"#/definitions/TwitterAccounts"}},"400":{"description":"Bad Request"}},"schemes":["https"],"security":[{"jwt":["api:access"]}]}},"/expeditions/{expedition_id}/team":{"post":{"tags":["team"],"summary":"add team","description":"Add a team\n\nRequired security scopes:\n  * `api:access`","operationId":"team#add","produces":["application/vnd.app.team+json"],"parameters":[{"name":"expedition_id","in":"path","required":true,"type":"integer"},{"name":"payload","in":"body","required":true,"schema":{"$ref":"#/definitions/AddTeamPayload"}}],"responses":{"200":{"description":"OK","schema":{"$ref":"#/definitions/Team"}},"400":{"description":"Bad Request"}},"schemes":["https"],"security":[{"jwt":["api:access"]}]}},"/expeditions/{expedition_id}/teams":{"get":{"tags":["team"],"summary":"list id team","description":"List an expedition's teams\n\nRequired security scopes:\n  * `api:access`","operationId":"team#list id","produces":["application/vnd.app.teams+json"],"parameters":[{"name":"expedition_id","in":"path","required":true,"type":"integer"}],"responses":{"200":{"description":"OK","schema":{"$ref":"#/definitions/Teams"}},"400":{"description":"Bad Request"}},"schemes":["https"],"security":[{"jwt":["api:access"]}]}},"/inputs/twitter-accounts/{input_id}":{"get":{"tags":["twitter"],"summary":"get id twitter","description":"Get a Twitter account input\n\nRequired security scopes:\n  * `api:access`","operationId":"twitter#get id","produces":["application/vnd.app.twitter_account+json"],"parameters":[{"name":"input_id","in":"path","required":true,"type":"integer"}],"responses":{"200":{"description":"OK","schema":{"$ref":"#/definitions/TwitterAccount"}},"400":{"description":"Bad Request"}},"schemes":["https"],"security":[{"jwt":["api:access"]}]}},"/login":{"post":{"tags":["user"],"summary":"login user","description":"Creates a valid JWT given login credentials.","operationId":"user#login","parameters":[{"name":"payload","in":"body","required":true,"schema":{"$ref":"#/definitions/LoginPayload"}}],"responses":{"204":{"description":"No Content","headers":{"Authorization":{"description":"Generated JWT","type":"string"}}},"400":{"description":"Bad Request"},"401":{"description":"Unauthorized"}},"schemes":["https"]}},"/logout":{"post":{"tags":["user"],"summary":"logout user","description":"Creates a valid JWT given login credentials.\n\nRequired security scopes:\n  * `api:access`","operationId":"user#logout","responses":{"204":{"description":"No Content"},"400":{"description":"Bad Request"}},"schemes":["https"],"security":[{"jwt":["api:access"]}]}},"/project":{"post":{"tags":["project"],"summary":"add project","description":"Add a project\n\nRequired security scopes:\n  * `api:access`","operationId":"project#add","produces":["application/vnd.app.project+json"],"parameters":[{"name":"payload","in":"body","required":true,"schema":{"$ref":"#/definitions/AddProjectPayload"}}],"responses":{"200":{"description":"OK","schema":{"$ref":"#/definitions/Project"}},"400":{"description":"Bad Request"}},"schemes":["https"],"security":[{"jwt":["api:access"]}]}},"/projects":{"get":{"tags":["project"],"summary":"list project","description":"List projects\n\nRequired security scopes:\n  * `api:access`","operationId":"project#list","produces":["application/vnd.app.projects+json"],"responses":{"200":{"description":"OK","schema":{"$ref":"#/definitions/Projects"}},"400":{"description":"Bad Request"}},"schemes":["https"],"security":[{"jwt":["api:access"]}]}},"/projects/@/{project}":{"get":{"tags":["project"],"summary":"get project","description":"Get a project\n\nRequired security scopes:\n  * `api:access`","operationId":"project#get","produces":["application/vnd.app.project+json"],"parameters":[{"name":"project","in":"path","description":"Project slug","required":true,"type":"string","pattern":"^[[:alnum:]]+(-[[:alnum:]]+)*$"}],"responses":{"200":{"description":"OK","schema":{"$ref":"#/definitions/Project"}},"400":{"description":"Bad Request"}},"schemes":["https"],"security":[{"jwt":["api:access"]}]}},"/projects/@/{project}/administrators":{"get":{"tags":["administrator"],"summary":"list administrator","description":"List an project's administrators\n\nRequired security scopes:\n  * `api:access`","operationId":"administrator#list","produces":["application/vnd.app.administrators+json"],"parameters":[{"name":"project","in":"path","description":"Project slug","required":true,"type":"string","pattern":"^[[:alnum:]]+(-[[:alnum:]]+)*$"}],"responses":{"200":{"description":"OK","schema":{"$ref":"#/definitions/ProjectAdministrators"}},"400":{"description":"Bad Request"}},"schemes":["https"],"security":[{"jwt":["api:access"]}]}},"/projects/@/{project}/administrators/@/{username}":{"get":{"tags":["administrator"],"summary":"get administrator","description":"Get an administrator\n\nRequired security scopes:\n  * `api:access`","operationId":"administrator#get","produces":["application/vnd.app.administrator+json"],"parameters":[{"name":"project","in":"path","description":"Project slug","required":true,"type":"string","pattern":"^[[:alnum:]]+(-[[:alnum:]]+)*$"},{"name":"username","in":"path","description":"Username","required":true,"type":"string","pattern":"^[[:alnum:]]+(-[[:alnum:]]+)*$"}],"responses":{"200":{"description":"OK","schema":{"$ref":"#/definitions/ProjectAdministrator"}}},"schemes":["https"],"security":[{"jwt":["api:access"]}]}},"/projects/@/{project}/expeditions":{"get":{"tags":["expedition"],"summary":"list expedition","description":"List a project's expeditions\n\nRequired security scopes:\n  * `api:access`","operationId":"expedition#list","produces":["application/vnd.app.expeditions+json"],"parameters":[{"name":"project","in":"path","description":"Project slug","required":true,"type":"string","pattern":"^[[:alnum:]]+(-[[:alnum:]]+)*$"}],"responses":{"200":{"description":"OK","schema":{"$ref":"#/definitions/Expeditions"}},"400":{"description":"Bad Request"}},"schemes":["https"],"security":[{"jwt":["api:access"]}]}},"/projects/@/{project}/expeditions/@/{expedition}":{"get":{"tags":["expedition"],"summary":"get expedition","description":"Add a expedition\n\nRequired security scopes:\n  * `api:access`","operationId":"expedition#get","produces":["application/vnd.app.expedition+json"],"parameters":[{"name":"expedition","in":"path","description":"Expedition slug","required":true,"type":"string","pattern":"^[[:alnum:]]+(-[[:alnum:]]+)*$"},{"name":"project","in":"path","description":"Project slug","required":true,"type":"string","pattern":"^[[:alnum:]]+(-[[:alnum:]]+)*$"}],"responses":{"200":{"description":"OK","schema":{"$ref":"#/definitions/Expedition"}},"400":{"description":"Bad Request"}},"schemes":["https"],"security":[{"jwt":["api:access"]}]}},"/projects/@/{project}/expeditions/@/{expedition}/inputs":{"get":{"tags":["input"],"summary":"list input","description":"List a project's inputs\n\nRequired security scopes:\n  * `api:access`","operationId":"input#list","produces":["application/vnd.app.inputs+json"],"parameters":[{"name":"expedition","in":"path","description":"Expedition slug","required":true,"type":"string","pattern":"^[[:alnum:]]+(-[[:alnum:]]+)*$"},{"name":"project","in":"path","description":"Project slug","required":true,"type":"string","pattern":"^[[:alnum:]]+(-[[:alnum:]]+)*$"}],"responses":{"200":{"description":"OK","schema":{"$ref":"#/definitions/Inputs"}},"400":{"description":"Bad Request"}},"schemes":["https"],"security":[{"jwt":["api:access"]}]}},"/projects/@/{project}/expeditions/@/{expedition}/inputs/twitter-accounts":{"get":{"tags":["twitter"],"summary":"list twitter","description":"List an expedition's Twitter account inputs\n\nRequired security scopes:\n  * `api:access`","operationId":"twitter#list","produces":["application/vnd.app.twitter_accounts+json"],"parameters":[{"name":"expedition","in":"path","description":"Expedition slug","required":true,"type":"string","pattern":"^[[:alnum:]]+(-[[:alnum:]]+)*$"},{"name":"project","in":"path","description":"Project slug","required":true,"type":"string","pattern":"^[[:alnum:]]+(-[[:alnum:]]+)*$"}],"responses":{"200":{"description":"OK","schema":{"$ref":"#/definitions/TwitterAccounts"}},"400":{"description":"Bad Request"}},"schemes":["https"],"security":[{"jwt":["api:access"]}]}},"/projects/@/{project}/expeditions/@/{expedition}/teams":{"get":{"tags":["team"],"summary":"list team","description":"List an expedition's teams\n\nRequired security scopes:\n  * `api:access`","operationId":"team#list","produces":["application/vnd.app.teams+json"],"parameters":[{"name":"expedition","in":"path","description":"Expedition slug","required":true,"type":"string","pattern":"^[[:alnum:]]+(-[[:alnum:]]+)*$"},{"name":"project","in":"path","description":"Project slug","required":true,"type":"string","pattern":"^[[:alnum:]]+(-[[:alnum:]]+)*$"}],"responses":{"200":{"description":"OK","schema":{"$ref":"#/definitions/Teams"}},"400":{"description":"Bad Request"}},"schemes":["https"],"security":[{"jwt":["api:access"]}]}},"/projects/@/{project}/expeditions/@/{expedition}/teams/@/{team}":{"get":{"tags":["team"],"summary":"get team","description":"Add a team\n\nRequired security scopes:\n  * `api:access`","operationId":"team#get","produces":["application/vnd.app.team+json"],"parameters":[{"name":"expedition","in":"path","description":"Expedition slug","required":true,"type":"string","pattern":"^[[:alnum:]]+(-[[:alnum:]]+)*$"},{"name":"project","in":"path","description":"Project slug","required":true,"type":"string","pattern":"^[[:alnum:]]+(-[[:alnum:]]+)*$"},{"name":"team","in":"path","description":"Project slug","required":true,"type":"string","pattern":"^[[:alnum:]]+(-[[:alnum:]]+)*$"}],"responses":{"200":{"description":"OK","schema":{"$ref":"#/definitions/Team"}},"400":{"description":"Bad Request"}},"schemes":["https"],"security":[{"jwt":["api:access"]}]}},"/projects/@/{project}/expeditions/@/{expedition}/teams/@/{team}/members":{"get":{"tags":["member"],"summary":"list member","description":"List an team's members\n\nRequired security scopes:\n  * `api:access`","operationId":"member#list","produces":["application/vnd.app.members+json"],"parameters":[{"name":"expedition","in":"path","description":"Expedition slug","required":true,"type":"string","pattern":"^[[:alnum:]]+(-[[:alnum:]]+)*$"},{"name":"project","in":"path","description":"Project slug","required":true,"type":"string","pattern":"^[[:alnum:]]+(-[[:alnum:]]+)*$"},{"name":"team","in":"path","description":"Team slug","required":true,"type":"string","pattern":"^[[:alnum:]]+(-[[:alnum:]]+)*$"}],"responses":{"200":{"description":"OK","schema":{"$ref":"#/definitions/TeamMembers"}},"400":{"description":"Bad Request"}},"schemes":["https"],"security":[{"jwt":["api:access"]}]}},"/projects/@/{project}/expeditions/@/{expedition}/teams/@/{team}/members/@/{username}":{"get":{"tags":["member"],"summary":"get member","description":"Get a member\n\nRequired security scopes:\n  * `api:access`","operationId":"member#get","produces":["application/vnd.app.member+json"],"parameters":[{"name":"expedition","in":"path","description":"Expedition slug","required":true,"type":"string","pattern":"^[[:alnum:]]+(-[[:alnum:]]+)*$"},{"name":"project","in":"path","description":"Project slug","required":true,"type":"string","pattern":"^[[:alnum:]]+(-[[:alnum:]]+)*$"},{"name":"team","in":"path","description":"Team slug","required":true,"type":"string","pattern":"^[[:alnum:]]+(-[[:alnum:]]+)*$"},{"name":"username","in":"path","description":"Team slug","required":true,"type":"string","pattern":"^[[:alnum:]]+(-[[:alnum:]]+)*$"}],"responses":{"200":{"description":"OK","schema":{"$ref":"#/definitions/TeamMember"}}},"schemes":["https"],"security":[{"jwt":["api:access"]}]}},"/projects/{project_id}":{"get":{"tags":["project"],"summary":"get id project","description":"Get a project\n\nRequired security scopes:\n  * `api:access`","operationId":"project#get id","produces":["application/vnd.app.project+json"],"parameters":[{"name":"project_id","in":"path","required":true,"type":"integer"}],"responses":{"200":{"description":"OK","schema":{"$ref":"#/definitions/Project"}},"400":{"description":"Bad Request"}},"schemes":["https"],"security":[{"jwt":["api:access"]}]}},"/projects/{project_id}/administrator":{"post":{"tags":["administrator"],"summary":"add administrator","description":"Add an administrator to a project\n\nRequired security scopes:\n  * `api:access`","operationId":"administrator#add","produces":["application/vnd.app.administrator+json"],"parameters":[{"name":"project_id","in":"path","required":true,"type":"integer"},{"name":"payload","in":"body","required":true,"schema":{"$ref":"#/definitions/AddAdministratorPayload"}}],"responses":{"200":{"description":"OK","schema":{"$ref":"#/definitions/ProjectAdministrator"}},"400":{"description":"Bad Request"}},"schemes":["https"],"security":[{"jwt":["api:access"]}]}},"/projects/{project_id}/administrators":{"get":{"tags":["administrator"],"summary":"list id administrator","description":"List an projects's administrators\n\nRequired security scopes:\n  * `api:access`","operationId":"administrator#list id","produces":["application/vnd.app.administrators+json"],"parameters":[{"name":"project_id","in":"path","required":true,"type":"integer"}],"responses":{"200":{"description":"OK","schema":{"$ref":"#/definitions/ProjectAdministrators"}},"400":{"description":"Bad Request"}},"schemes":["https"],"security":[{"jwt":["api:access"]}]}},"/projects/{project_id}/administrators/{user_id}":{"get":{"tags":["administrator"],"summary":"get id administrator","description":"Get an administrator\n\nRequired security scopes:\n  * `api:access`","operationId":"administrator#get id","produces":["application/vnd.app.administrator+json"],"parameters":[{"name":"project_id","in":"path","required":true,"type":"integer"},{"name":"user_id","in":"path","required":true,"type":"integer"}],"responses":{"200":{"description":"OK","schema":{"$ref":"#/definitions/ProjectAdministrator"}}},"schemes":["https"],"security":[{"jwt":["api:access"]}]},"delete":{"tags":["administrator"],"summary":"delete administrator","description":"Remove an administrator from a project\n\nRequired security scopes:\n  * `api:access`","operationId":"administrator#delete","produces":["application/vnd.app.administrator+json"],"parameters":[{"name":"project_id","in":"path","required":true,"type":"integer"},{"name":"user_id","in":"path","required":true,"type":"integer"}],"responses":{"200":{"description":"OK","schema":{"$ref":"#/definitions/ProjectAdministrator"}},"400":{"description":"Bad Request"}},"schemes":["https"],"security":[{"jwt":["api:access"]}]}},"/projects/{project_id}/expedition":{"post":{"tags":["expedition"],"summary":"add expedition","description":"Add a expedition\n\nRequired security scopes:\n  * `api:access`","operationId":"expedition#add","produces":["application/vnd.app.expedition+json"],"parameters":[{"name":"project_id","in":"path","required":true,"type":"integer"},{"name":"payload","in":"body","required":true,"schema":{"$ref":"#/definitions/AddExpeditionPayload"}}],"responses":{"200":{"description":"OK","schema":{"$ref":"#/definitions/Expedition"}},"400":{"description":"Bad Request"}},"schemes":["https"],"security":[{"jwt":["api:access"]}]}},"/projects/{project_id}/expeditions":{"get":{"tags":["expedition"],"summary":"list id expedition","description":"List a project's expeditions\n\nRequired security scopes:\n  * `api:access`","operationId":"expedition#list id","produces":["application/vnd.app.expeditions+json"],"parameters":[{"name":"project_id","in":"path","required":true,"type":"integer"}],"responses":{"200":{"description":"OK","schema":{"$ref":"#/definitions/Expeditions"}},"400":{"description":"Bad Request"}},"schemes":["https"],"security":[{"jwt":["api:access"]}]}},"/refresh":{"post":{"tags":["user"],"summary":"refresh user","description":"Creates a valid JWT given a refresh token.","operationId":"user#refresh","parameters":[{"name":"payload","in":"body","required":true,"schema":{"$ref":"#/definitions/RefreshUserPayload"}}],"responses":{"204":{"description":"No Content","headers":{"Authorization":{"description":"Generated JWT","type":"string"}}},"401":{"description":"Unauthorized"}},"schemes":["https"]}},"/swagger.json":{"get":{"summary":"Download api/public/swagger/swagger.json","operationId":"swagger#/swagger.json","responses":{"200":{"description":"File downloaded","schema":{"type":"file"}}},"schemes":["https"]}},"/swagger.yaml":{"get":{"summary":"Download api/public/swagger/swagger.yaml","operationId":"swagger#/swagger.yaml","responses":{"200":{"description":"File downloaded","schema":{"type":"file"}}},"schemes":["https"]}},"/teams/{team_id}":{"get":{"tags":["team"],"summary":"get id team","description":"Add a team\n\nRequired security scopes:\n  * `api:access`","operationId":"team#get id","produces":["application/vnd.app.team+json"],"parameters":[{"name":"team_id","in":"path","required":true,"type":"integer"}],"responses":{"200":{"description":"OK","schema":{"$ref":"#/definitions/Team"}},"400":{"description":"Bad Request"}},"schemes":["https"],"security":[{"jwt":["api:access"]}]}},"/teams/{team_id}/member":{"post":{"tags":["member"],"summary":"add member","description":"Add a member to a team\n\nRequired security scopes:\n  * `api:access`","operationId":"member#add","produces":["application/vnd.app.member+json"],"parameters":[{"name":"team_id","in":"path","required":true,"type":"integer"},{"name":"payload","in":"body","required":true,"schema":{"$ref":"#/definitions/AddMemberPayload"}}],"responses":{"200":{"description":"OK","schema":{"$ref":"#/definitions/TeamMember"}},"400":{"description":"Bad Request"}},"schemes":["https"],"security":[{"jwt":["api:access"]}]}},"/teams/{team_id}/members":{"get":{"tags":["member"],"summary":"list id member","description":"List an teams's members\n\nRequired security scopes:\n  * `api:access`","operationId":"member#list id","produces":["application/vnd.app.members+json"],"parameters":[{"name":"team_id","in":"path","required":true,"type":"integer"}],"responses":{"200":{"description":"OK","schema":{"$ref":"#/definitions/TeamMembers"}},"400":{"description":"Bad Request"}},"schemes":["https"],"security":[{"jwt":["api:access"]}]}},"/teams/{team_id}/members/{user_id}":{"get":{"tags":["member"],"summary":"get id member","description":"Get a member\n\nRequired security scopes:\n  * `api:access`","operationId":"member#get id","produces":["application/vnd.app.member+json"],"parameters":[{"name":"team_id","in":"path","required":true,"type":"integer"},{"name":"user_id","in":"path","required":true,"type":"integer"}],"responses":{"200":{"description":"OK","schema":{"$ref":"#/definitions/TeamMember"}}},"schemes":["https"],"security":[{"jwt":["api:access"]}]},"delete":{"tags":["member"],"summary":"delete member","description":"Remove a member from a team\n\nRequired security scopes:\n  * `api:access`","operationId":"member#delete","produces":["application/vnd.app.member+json"],"parameters":[{"name":"team_id","in":"path","required":true,"type":"integer"},{"name":"user_id","in":"path","required":true,"type":"integer"}],"responses":{"200":{"description":"OK","schema":{"$ref":"#/definitions/TeamMember"}},"400":{"description":"Bad Request"}},"schemes":["https"],"security":[{"jwt":["api:access"]}]}},"/twitter/callback":{"get":{"tags":["twitter"],"summary":"callback twitter","description":"OAuth callback endpoint for Twitter","operationId":"twitter#callback","parameters":[{"name":"oauth_token","in":"query","required":true,"type":"string"},{"name":"oauth_verifier","in":"query","required":true,"type":"string"}],"responses":{"302":{"description":"Found","headers":{"Location":{"type":"string"}}},"400":{"description":"Bad Request"}},"schemes":["https"]}},"/user":{"get":{"tags":["user"],"summary":"get current user","description":"Get the authenticated user\n\nRequired security scopes:\n  * `api:access`","operationId":"user#get current","produces":["application/vnd.app.user+json"],"responses":{"200":{"description":"OK","schema":{"$ref":"#/definitions/User"}}},"schemes":["https"],"security":[{"jwt":["api:access"]}]},"post":{"tags":["user"],"summary":"add user","description":"Add a user","operationId":"user#add","produces":["application/vnd.app.user+json"],"parameters":[{"name":"payload","in":"body","required":true,"schema":{"$ref":"#/definitions/AddUserPayload"}}],"responses":{"200":{"description":"OK","schema":{"$ref":"#/definitions/User"}},"400":{"description":"Bad Request"}},"schemes":["https"]}},"/user/projects":{"get":{"tags":["project"],"summary":"list current project","description":"List the authenticated user's projects\n\nRequired security scopes:\n  * `api:access`","operationId":"project#list current","produces":["application/vnd.app.projects+json"],"responses":{"200":{"description":"OK","schema":{"$ref":"#/definitions/Projects"}},"400":{"description":"Bad Request"}},"schemes":["https"],"security":[{"jwt":["api:access"]}]}},"/users":{"get":{"tags":["user"],"summary":"list user","description":"List users\n\nRequired security scopes:\n  * `api:access`","operationId":"user#list","produces":["application/vnd.app.users+json"],"responses":{"200":{"description":"OK","schema":{"$ref":"#/definitions/Users"}}},"schemes":["https"],"security":[{"jwt":["api:access"]}]}},"/users/@/{username}":{"get":{"tags":["user"],"summary":"get user","description":"Get a user\n\nRequired security scopes:\n  * `api:access`","operationId":"user#get","produces":["application/vnd.app.user+json"],"parameters":[{"name":"username","in":"path","required":true,"type":"string"}],"responses":{"200":{"description":"OK","schema":{"$ref":"#/definitions/User"}}},"schemes":["https"],"security":[{"jwt":["api:access"]}]}},"/users/{user_id}":{"get":{"tags":["user"],"summary":"get id user","description":"Get a user\n\nRequired security scopes:\n  * `api:access`","operationId":"user#get id","produces":["application/vnd.app.user+json"],"parameters":[{"name":"user_id","in":"path","required":true,"type":"integer"}],"responses":{"200":{"description":"OK","schema":{"$ref":"#/definitions/User"}}},"schemes":["https"],"security":[{"jwt":["api:access"]}]}},"/validate":{"get":{"tags":["user"],"summary":"validate user","description":"Validate a user's email address.","operationId":"user#validate","parameters":[{"name":"token","in":"query","required":true,"type":"string"}],"responses":{"302":{"description":"Found","headers":{"Location":{"type":"string"}}},"401":{"description":"Unauthorized"}},"schemes":["https"]}}},"definitions":{"AddAdministratorPayload":{"title":"AddAdministratorPayload","type":"object","properties":{"user_id":{"type":"integer","example":1682164589291537836,"format":"int64"}},"example":{"user_id":1682164589291537836},"required":["user_id"]},"AddExpeditionPayload":{"title":"AddExpeditionPayload","type":"object","properties":{"description":{"type":"string","example":"Asperiores nostrum."},"name":{"type":"string","example":"Dignissimos aut repellendus quam soluta odio."},"slug":{"type":"string","example":"3n7ahu8r8v","pattern":"^[[:alnum:]]+(-[[:alnum:]]+)*$","maxLength":40}},"example":{"description":"Asperiores nostrum.","name":"Dignissimos aut repellendus quam soluta odio.","slug":"3n7ahu8r8v"},"required":["name","slug","description"]},"AddMemberPayload":{"title":"AddMemberPayload","type":"object","properties":{"role":{"type":"string","example":"A voluptas."},"user_id":{"type":"integer","example":657652285070733369,"format":"int64"}},"example":{"role":"A voluptas.","user_id":657652285070733369},"required":["user_id","role"]},"AddProjectPayload":{"title":"AddProjectPayload","type":"object","properties":{"description":{"type":"string","example":"Itaque qui sequi."},"name":{"type":"string","example":"Laudantium quo eos fuga ab repudiandae."},"slug":{"type":"string","example":"ic2d6hce00","pattern":"^[[:alnum:]]+(-[[:alnum:]]+)*$","maxLength":40}},"example":{"description":"Itaque qui sequi.","name":"Laudantium quo eos fuga ab repudiandae.","slug":"ic2d6hce00"},"required":["name","slug","description"]},"AddTeamPayload":{"title":"AddTeamPayload","type":"object","properties":{"description":{"type":"string","example":"Consequatur ullam sed magni."},"name":{"type":"string","example":"Et blanditiis debitis eos iure ea."},"slug":{"type":"string","example":"jv73wy8mr3","pattern":"^[[:alnum:]]+(-[[:alnum:]]+)*$","maxLength":40}},"example":{"description":"Consequatur ullam sed magni.","name":"Et blanditiis debitis eos iure ea.","slug":"jv73wy8mr3"},"required":["name","slug","description"]},"AddUserPayload":{"title":"AddUserPayload","type":"object","properties":{"email":{"type":"string","example":"jailyn.ernser@brekkeankunding.com","format":"email"},"invite_token":{"type":"string","example":"Occaecati occaecati omnis sint."},"password":{"type":"string","example":"y52dmi76ci","minLength":10},"username":{"type":"string","example":"gd200jauck","pattern":"^[[:alnum:]]+(-[[:alnum:]]+)*$","maxLength":40}},"example":{"email":"jailyn.ernser@brekkeankunding.com","invite_token":"Occaecati occaecati omnis sint.","password":"y52dmi76ci","username":"gd200jauck"},"required":["email","username","password","invite_token"]},"Expedition":{"title":"Mediatype identifier: application/vnd.app.expedition+json; view=default","type":"object","properties":{"description":{"type":"string","example":"Qui possimus porro quaerat."},"id":{"type":"integer","example":1240241157333250549,"format":"int64"},"name":{"type":"string","example":"Saepe facilis quis blanditiis recusandae est."},"slug":{"type":"string","example":"ap0fuesxsv","pattern":"^[[:alnum:]]+(-[[:alnum:]]+)*$","maxLength":40}},"description":"Expedition media type (default view)","example":{"description":"Qui possimus porro quaerat.","id":1240241157333250549,"name":"Saepe facilis quis blanditiis recusandae est.","slug":"ap0fuesxsv"},"required":["id","name","slug","description"]},"ExpeditionCollection":{"title":"Mediatype identifier: application/vnd.app.expedition+json; type=collection; view=default","type":"array","items":{"$ref":"#/definitions/Expedition"},"description":"ExpeditionCollection is the media type for an array of Expedition (default view)","example":[{"description":"Qui possimus porro quaerat.","id":1240241157333250549,"name":"Saepe facilis quis blanditiis recusandae est.","slug":"ap0fuesxsv"},{"description":"Qui possimus porro quaerat.","id":1240241157333250549,"name":"Saepe facilis quis blanditiis recusandae est.","slug":"ap0fuesxsv"},{"description":"Qui possimus porro quaerat.","id":1240241157333250549,"name":"Saepe facilis quis blanditiis recusandae est.","slug":"ap0fuesxsv"}]},"Expeditions":{"title":"Mediatype identifier: application/vnd.app.expeditions+json; view=default","type":"object","properties":{"expeditions":{"$ref":"#/definitions/ExpeditionCollection"}},"description":"Expeditions media type (default view)","example":{"expeditions":[{"description":"Qui possimus porro quaerat.","id":1240241157333250549,"name":"Saepe facilis quis blanditiis recusandae est.","slug":"ap0fuesxsv"}]},"required":["expeditions"]},"Inputs":{"title":"Mediatype identifier: application/vnd.app.inputs+json; view=default","type":"object","properties":{"twitter_accounts":{"$ref":"#/definitions/TwitterAccountCollection"}},"description":"Inputs media type (default view)","example":{"twitter_accounts":[{"expedition_id":4464267130479644100,"id":368251371561159851,"screen_name":"Laboriosam aut voluptatum.","twitter_account_id":2272611424157726775}]}},"Location":{"title":"Mediatype identifier: application/vnd.app.location+json; view=default","type":"object","properties":{"location":{"type":"string","example":"http://stehr.net/lura","format":"uri"}},"description":"Location media type (default view)","example":{"location":"http://stehr.net/lura"},"required":["location"]},"LoginPayload":{"title":"LoginPayload","type":"object","properties":{"password":{"type":"string","example":"p4mrpluru5","minLength":10},"username":{"type":"string","example":"rgjkna1y63","pattern":"^[[:alnum:]]+(-[[:alnum:]]+)*$","maxLength":40}},"example":{"password":"p4mrpluru5","username":"rgjkna1y63"},"required":["username","password"]},"Project":{"title":"Mediatype identifier: application/vnd.app.project+json; view=default","type":"object","properties":{"description":{"type":"string","example":"Eum enim deleniti sint velit qui."},"id":{"type":"integer","example":134549257128040152,"format":"int64"},"name":{"type":"string","example":"Quidem quis fugit commodi ut."},"slug":{"type":"string","example":"7z8os8qw8b","pattern":"^[[:alnum:]]+(-[[:alnum:]]+)*$","maxLength":40}},"description":"Project media type (default view)","example":{"description":"Eum enim deleniti sint velit qui.","id":134549257128040152,"name":"Quidem quis fugit commodi ut.","slug":"7z8os8qw8b"},"required":["id","name","slug","description"]},"ProjectAdministrator":{"title":"Mediatype identifier: application/vnd.app.administrator+json; view=default","type":"object","properties":{"project_id":{"type":"integer","example":1283342708539166643,"format":"int64"},"user_id":{"type":"integer","example":6297057674710826123,"format":"int64"}},"description":"ProjectAdministrator media type (default view)","example":{"project_id":1283342708539166643,"user_id":6297057674710826123},"required":["project_id","user_id"]},"ProjectAdministratorCollection":{"title":"Mediatype identifier: application/vnd.app.administrator+json; type=collection; view=default","type":"array","items":{"$ref":"#/definitions/ProjectAdministrator"},"description":"ProjectAdministratorCollection is the media type for an array of ProjectAdministrator (default view)","example":[{"project_id":1283342708539166643,"user_id":6297057674710826123},{"project_id":1283342708539166643,"user_id":6297057674710826123},{"project_id":1283342708539166643,"user_id":6297057674710826123}]},"ProjectAdministrators":{"title":"Mediatype identifier: application/vnd.app.administrators+json; view=default","type":"object","properties":{"administrators":{"$ref":"#/definitions/ProjectAdministratorCollection"}},"description":"ProjectAdministrators media type (default view)","example":{"administrators":[{"project_id":1283342708539166643,"user_id":6297057674710826123},{"project_id":1283342708539166643,"user_id":6297057674710826123},{"project_id":1283342708539166643,"user_id":6297057674710826123}]},"required":["administrators"]},"ProjectCollection":{"title":"Mediatype identifier: application/vnd.app.project+json; type=collection; view=default","type":"array","items":{"$ref":"#/definitions/Project"},"description":"ProjectCollection is the media type for an array of Project (default view)","example":[{"description":"Eum enim deleniti sint velit qui.","id":134549257128040152,"name":"Quidem quis fugit commodi ut.","slug":"7z8os8qw8b"},{"description":"Eum enim deleniti sint velit qui.","id":134549257128040152,"name":"Quidem quis fugit commodi ut.","slug":"7z8os8qw8b"}]},"Projects":{"title":"Mediatype identifier: application/vnd.app.projects+json; view=default","type":"object","properties":{"projects":{"$ref":"#/definitions/ProjectCollection"}},"description":"Projects media type (default view)","example":{"projects":[{"description":"Eum enim deleniti sint velit qui.","id":134549257128040152,"name":"Quidem quis fugit commodi ut.","slug":"7z8os8qw8b"}]},"required":["projects"]},"RefreshUserPayload":{"title":"RefreshUserPayload","type":"object","properties":{"refresh_token":{"type":"string","example":"Vel quisquam voluptatem doloribus."}},"example":{"refresh_token":"Vel quisquam voluptatem doloribus."},"required":["refresh_token"]},"Team":{"title":"Mediatype identifier: application/vnd.app.team+json; view=default","type":"object","properties":{"description":{"type":"string","example":"Ipsam reprehenderit totam dolorem impedit hic."},"id":{"type":"integer","example":6040333430350640356,"format":"int64"},"name":{"type":"string","example":"Repellendus cupiditate nemo doloribus."},"slug":{"type":"string","example":"bux7jxef7u","pattern":"^[[:alnum:]]+(-[[:alnum:]]+)*$","maxLength":40}},"description":"Team media type (default view)","example":{"description":"Ipsam reprehenderit totam dolorem impedit hic.","id":6040333430350640356,"name":"Repellendus cupiditate nemo doloribus.","slug":"bux7jxef7u"},"required":["id","name","slug","description"]},"TeamCollection":{"title":"Mediatype identifier: application/vnd.app.team+json; type=collection; view=default","type":"array","items":{"$ref":"#/definitions/Team"},"description":"TeamCollection is the media type for an array of Team (default view)","example":[{"description":"Ipsam reprehenderit totam dolorem impedit hic.","id":6040333430350640356,"name":"Repellendus cupiditate nemo doloribus.","slug":"bux7jxef7u"},{"description":"Ipsam reprehenderit totam dolorem impedit hic.","id":6040333430350640356,"name":"Repellendus cupiditate nemo doloribus.","slug":"bux7jxef7u"},{"description":"Ipsam reprehenderit totam dolorem impedit hic.","id":6040333430350640356,"name":"Repellendus cupiditate nemo doloribus.","slug":"bux7jxef7u"}]},"TeamMember":{"title":"Mediatype identifier: application/vnd.app.member+json; view=default","type":"object","properties":{"role":{"type":"string","example":"Et amet amet reiciendis."},"team_id":{"type":"integer","example":5857079281444670451,"format":"int64"},"user_id":{"type":"integer","example":5307110733935865259,"format":"int64"}},"description":"TeamMember media type (default view)","example":{"role":"Et amet amet reiciendis.","team_id":5857079281444670451,"user_id":5307110733935865259},"required":["team_id","user_id","role"]},"TeamMemberCollection":{"title":"Mediatype identifier: application/vnd.app.member+json; type=collection; view=default","type":"array","items":{"$ref":"#/definitions/TeamMember"},"description":"TeamMemberCollection is the media type for an array of TeamMember (default view)","example":[{"role":"Et amet amet reiciendis.","team_id":5857079281444670451,"user_id":5307110733935865259},{"role":"Et amet amet reiciendis.","team_id":5857079281444670451,"user_id":5307110733935865259},{"role":"Et amet amet reiciendis.","team_id":5857079281444670451,"user_id":5307110733935865259}]},"TeamMembers":{"title":"Mediatype identifier: application/vnd.app.members+json; view=default","type":"object","properties":{"members":{"$ref":"#/definitions/TeamMemberCollection"}},"description":"TeamMembers media type (default view)","example":{"members":[{"role":"Et amet amet reiciendis.","team_id":5857079281444670451,"user_id":5307110733935865259}]},"required":["members"]},"Teams":{"title":"Mediatype identifier: application/vnd.app.teams+json; view=default","type":"object","properties":{"teams":{"$ref":"#/definitions/TeamCollection"}},"description":"Teams media type (default view)","example":{"teams":[{"description":"Ipsam reprehenderit totam dolorem impedit hic.","id":6040333430350640356,"name":"Repellendus cupiditate nemo doloribus.","slug":"bux7jxef7u"}]},"required":["teams"]},"TwitterAccount":{"title":"Mediatype identifier: application/vnd.app.twitter_account+json; view=default","type":"object","properties":{"expedition_id":{"type":"integer","example":4464267130479644100,"format":"int64"},"id":{"type":"integer","example":368251371561159851,"format":"int64"},"screen_name":{"type":"string","example":"Laboriosam aut voluptatum."},"twitter_account_id":{"type":"integer","example":2272611424157726775,"format":"int64"}},"description":"TwitterAccount media type (default view)","example":{"expedition_id":4464267130479644100,"id":368251371561159851,"screen_name":"Laboriosam aut voluptatum.","twitter_account_id":2272611424157726775},"required":["id","expedition_id","twitter_account_id","screen_name"]},"TwitterAccountCollection":{"title":"Mediatype identifier: application/vnd.app.twitter_account+json; type=collection; view=default","type":"array","items":{"$ref":"#/definitions/TwitterAccount"},"description":"TwitterAccountCollection is the media type for an array of TwitterAccount (default view)","example":[{"expedition_id":4464267130479644100,"id":368251371561159851,"screen_name":"Laboriosam aut voluptatum.","twitter_account_id":2272611424157726775},{"expedition_id":4464267130479644100,"id":368251371561159851,"screen_name":"Laboriosam aut voluptatum.","twitter_account_id":2272611424157726775}]},"TwitterAccounts":{"title":"Mediatype identifier: application/vnd.app.twitter_accounts+json; view=default","type":"object","properties":{"twitter_accounts":{"$ref":"#/definitions/TwitterAccountCollection"}},"description":"TwitterAccounts media type (default view)","example":{"twitter_accounts":[{"expedition_id":4464267130479644100,"id":368251371561159851,"screen_name":"Laboriosam aut voluptatum.","twitter_account_id":2272611424157726775}]},"required":["twitter_accounts"]},"User":{"title":"Mediatype identifier: application/vnd.app.user+json; view=default","type":"object","properties":{"id":{"type":"integer","example":5545350766309727043,"format":"int64"},"username":{"type":"string","example":"gzslj0tddk","pattern":"^[[:alnum:]]+(-[[:alnum:]]+)*$","maxLength":40}},"description":"User media type (default view)","example":{"id":5545350766309727043,"username":"gzslj0tddk"},"required":["id","username"]},"UserCollection":{"title":"Mediatype identifier: application/vnd.app.user+json; type=collection; view=default","type":"array","items":{"$ref":"#/definitions/User"},"description":"UserCollection is the media type for an array of User (default view)","example":[{"id":5545350766309727043,"username":"gzslj0tddk"},{"id":5545350766309727043,"username":"gzslj0tddk"},{"id":5545350766309727043,"username":"gzslj0tddk"}]},"Users":{"title":"Mediatype identifier: application/vnd.app.users+json; view=default","type":"object","properties":{"users":{"$ref":"#/definitions/UserCollection"}},"description":"Users media type (default view)","example":{"users":[{"id":5545350766309727043,"username":"gzslj0tddk"}]},"required":["users"]}},"responses":{"BadRequest":{"description":"Bad Request"},"NoContent":{"description":"No Content"},"Unauthorized":{"description":"Unauthorized"}},"securityDefinitions":{"jwt":{"type":"apiKey","description":"\n\n**Security Scopes**:\n  * `api:access`: API access","name":"Authorization","in":"header"}}}